{
  "user_links": [{
    "$priority": 0,
    "activated": true,
    "allowedGroups": [],
    "anonymous": false,
    "description": {
      "de_DE": "Open Source Team Communication",
      "en_US": "Open Source Team Communication"
    },
    "dn": "cn=rocketchat,cn=entry,cn=portals,cn=univention,dc=intranet,dc=wiesenthal,dc=de",
    "linkTarget": "useportaldefault",
    "links": ["https://10.200.4.50/rocketchat/", "http://10.200.4.50/rocketchat/", "http://master50.intranet.wiesenthal.de/rocketchat/", "https://master50.intranet.wiesenthal.de/rocketchat/"],
    "logo_name": "./icons/entries/rocketchat.svg",
    "name": {
      "de_DE": "Rocket.Chat",
      "en_US": "Rocket.Chat"
    }
  }],
  "menu_links": [{
    "$priority": 0,
    "activated": true,
    "allowedGroups": [],
    "anonymous": false,
    "description": {
      "de_DE": "Cloud L\u00f6sung f\u00fcr Filesync und -share",
      "en_US": "Cloud solution for data and file sync and share"
    },
    "dn": "cn=owncloud,cn=entry,cn=portals,cn=univention,dc=intranet,dc=wiesenthal,dc=de",
    "linkTarget": "useportaldefault",
    "links": ["http://master50.intranet.wiesenthal.de/owncloud", "https://10.200.4.50/owncloud", "https://master50.intranet.wiesenthal.de/owncloud", "http://10.200.4.50/owncloud"],
    "logo_name": "./icons/entries/owncloud.svg",
    "name": {
      "de_DE": "ownCloud",
      "en_US": "ownCloud"
    },
    "sub_menu": [
      {
        "name": {
          "de_DE": "SubItem 1 DE",
          "en_US": "SubItem 1 EN"
        }
      },
      {
        "name": {
          "de_DE": "SubItem 2 DE",
          "en_US": "SubItem 2 EN"
        }
      }
    ]
  },
  {
    "$priority": 0,
    "activated": true,
    "allowedGroups": [],
    "anonymous": false,
    "description": {
      "de_DE": "Cloud L\u00f6sung f\u00fcr Filesync und -share",
      "en_US": "Cloud solution for data and file sync and share"
    },
    "dn": "cn=owncloud,cn=entry,cn=portals,cn=univention,dc=intranet,dc=wiesenthal,dc=de",
    "linkTarget": "useportaldefault",
    "links": ["#", "#", "#", "#"],
    "logo_name": "./icons/entries/owncloud.svg",
    "name": {
      "de_DE": "Univention Blog",
      "en_US": "Univention Blog"
    },
    "sub_menu": [
      {
        "name": {
          "de_DE": "SubItem 3 DE",
          "en_US": "SubItem 3 EN"
        }
      }
    ]
  }]
}