{
  "user_links": [{
    "$priority": 0,
    "activated": true,
    "allowedGroups": [],
    "anonymous": false,
    "description": {
      "de_DE": "Open Source Team Communication",
      "en_US": "Open Source Team Communication"
    },
    "dn": "cn=rocketchat,cn=entry,cn=portals,cn=univention,dc=intranet,dc=wiesenthal,dc=de",
    "linkTarget": "useportaldefault",
    "links": ["https://10.200.4.50/rocketchat/", "http://10.200.4.50/rocketchat/", "http://master50.intranet.wiesenthal.de/rocketchat/", "https://master50.intranet.wiesenthal.de/rocketchat/"],
    "logo_name": "./icons/entries/rocketchat.svg",
    "name": {
      "de_DE": "Rocket.Chat",
      "en_US": "Rocket.Chat"
    }
  }],
  "menu_links": [{
    "$priority": 0,
    "activated": true,
    "allowedGroups": [],
    "anonymous": false,
    "description": {
      "de_DE": "Cloud L\u00f6sung f\u00fcr Filesync und -share",
      "en_US": "Cloud solution for data and file sync and share"
    },
    "dn": "cn=owncloud,cn=entry,cn=portals,cn=univention,dc=intranet,dc=wiesenthal,dc=de",
    "linkTarget": "useportaldefault",
    "links": ["http://master50.intranet.wiesenthal.de/owncloud", "https://10.200.4.50/owncloud", "https://master50.intranet.wiesenthal.de/owncloud", "http://10.200.4.50/owncloud"],
    "logo_name": "./icons/entries/owncloud.svg",
    "name": {
      "de_DE": "ownCloud",
      "en_US": "ownCloud"
    }
  }],
  "entries": {
    "cn=owncloud,cn=entry,cn=portals,cn=univention,dc=intranet,dc=wiesenthal,dc=de": {
      "activated": true,
      "allowedGroups": [],
      "anonymous": false,
      "backgroundColor": null,
      "description": {
        "de_DE": "Cloud L\u00f6sung f\u00fcr Filesync und -share",
        "en_US": "Cloud solution for data and file sync and share"
      },
      "dn": "cn=owncloud,cn=entry,cn=portals,cn=univention,dc=intranet,dc=wiesenthal,dc=de",
      "linkTarget": "useportaldefault",
      "links": ["http://master50.intranet.wiesenthal.de/owncloud", "https://10.200.4.50/owncloud", "https://master50.intranet.wiesenthal.de/owncloud", "http://10.200.4.50/owncloud"],
      "logo_name": "./icons/entries/owncloud.svg",
      "name": {
        "de_DE": "ownCloud",
        "en_US": "ownCloud"
      }
    },
    "cn=owncloud-admindoc,cn=entry,cn=portals,cn=univention,dc=intranet,dc=wiesenthal,dc=de": {
      "activated": true,
      "allowedGroups": [],
      "anonymous": true,
      "backgroundColor": null,
      "description": {
        "de_DE": "ownCloud Administrations-Handbuch (in Englisch)",
        "en_US": "ownCloud Administration Manual"
      },
      "dn": "cn=owncloud-admindoc,cn=entry,cn=portals,cn=univention,dc=intranet,dc=wiesenthal,dc=de",
      "linkTarget": "useportaldefault",
      "links": ["https://doc.owncloud.com/server/10.0/admin_manual/"],
      "logo_name": "./icons/entries/owncloud-admindoc.svg",
      "name": {
        "de_DE": "Admin Handbuch",
        "en_US": "Admin Manual"
      }
    },
    "cn=rocketchat,cn=entry,cn=portals,cn=univention,dc=intranet,dc=wiesenthal,dc=de": {
      "activated": true,
      "allowedGroups": [],
      "anonymous": false,
      "backgroundColor": null,
      "description": {
        "de_DE": "Open Source Team Communication",
        "en_US": "Open Source Team Communication"
      },
      "dn": "cn=rocketchat,cn=entry,cn=portals,cn=univention,dc=intranet,dc=wiesenthal,dc=de",
      "linkTarget": "useportaldefault",
      "links": ["https://10.200.4.50/rocketchat/", "http://10.200.4.50/rocketchat/", "http://master50.intranet.wiesenthal.de/rocketchat/", "https://master50.intranet.wiesenthal.de/rocketchat/"],
      "logo_name": "./icons/entries/rocketchat.svg",
      "name": {
        "de_DE": "Rocket.Chat",
        "en_US": "Rocket.Chat"
      }
    },
    "cn=self-service,cn=entry,cn=portals,cn=univention,dc=intranet,dc=wiesenthal,dc=de": {
      "activated": true,
      "allowedGroups": [],
      "anonymous": false,
      "backgroundColor": null,
      "description": {
        "de_DE": "Self-Service-Module (Passwort \u00e4ndern und zur\u00fccksetzen)",
        "en_US": "Self Service modules (change and recover passwords)",
        "fr_FR": "Module de libre-service (changer et r\u00e9initialiser des mots de passe)"
      },
      "dn": "cn=self-service,cn=entry,cn=portals,cn=univention,dc=intranet,dc=wiesenthal,dc=de",
      "linkTarget": "useportaldefault",
      "links": ["https://master50.intranet.wiesenthal.de/univention/self-service/#page=passwordchange", "https://10.200.4.50/univention/self-service/#page=passwordchange"],
      "logo_name": null,
      "name": {
        "de_DE": "Passwort \u00e4ndern",
        "en_US": "Change password",
        "fr_FR": "Changer le mot de passe"
      }
    },
    "cn=umc-domain,cn=entry,cn=portals,cn=univention,dc=intranet,dc=wiesenthal,dc=de": {
      "activated": true,
      "allowedGroups": [],
      "anonymous": false,
      "backgroundColor": null,
      "description": {
        "de_DE": "Univention Management Console zur Ver\u00adwal\u00adtung der UCS-Dom\u00e4ne und des lokalen Systems",
        "en_US": "Univention Management Console for admin\u00adis\u00adtra\u00adting the UCS domain and the local system",
        "fr_FR": "Console de gestion Univention pour admin\u00adis\u00adtrer le domaine UCS et le syst\u00e8me local"
      },
      "dn": "cn=umc-domain,cn=entry,cn=portals,cn=univention,dc=intranet,dc=wiesenthal,dc=de",
      "linkTarget": "newwindow",
      "links": ["/univention/management/"],
      "logo_name": "./icons/entries/umc-domain.svg",
      "name": {
        "de_DE": "System- und Dom\u00e4neneinstellungen",
        "en_US": "System and domain settings",
        "fr_FR": "R\u00e9glages du syst\u00e8me et du domaine"
      }
    },
    "cn=univentionblog,cn=entry,cn=portals,cn=univention,dc=intranet,dc=wiesenthal,dc=de": {
      "activated": true,
      "allowedGroups": [],
      "anonymous": false,
      "backgroundColor": null,
      "description": {
        "de_DE": "News, Tipps und Best Practices",
        "en_US": "News, tips and best practices",
        "fr_FR": "Nouvelles, conseils et bonne pratique"
      },
      "dn": "cn=univentionblog,cn=entry,cn=portals,cn=univention,dc=intranet,dc=wiesenthal,dc=de",
      "linkTarget": "newwindow",
      "links": ["https://www.univention.com/news/blog-en/"],
      "logo_name": "./icons/entries/univentionblog.png",
      "name": {
        "de_DE": "Univention Blog 3",
        "en_US": "Univention Blog 3",
        "fr_FR": "Univention Blog"
      }
    }
  },
  "folders": {
    "cn=folder1,cn=folder,cn=portals,cn=univention,dc=intranet,dc=wiesenthal,dc=de": {
      "dn": "cn=folder1,cn=folder,cn=portals,cn=univention,dc=intranet,dc=wiesenthal,dc=de",
      "entries": ["cn=univentionblog,cn=entry,cn=portals,cn=univention,dc=intranet,dc=wiesenthal,dc=de"],
      "name": {
        "de_DE": "Favoriten",
        "en_US": "Favoriten"
      }
    },
    "cn=folder2,cn=folder,cn=portals,cn=univention,dc=intranet,dc=wiesenthal,dc=de": {
      "dn": "cn=folder2,cn=folder,cn=portals,cn=univention,dc=intranet,dc=wiesenthal,dc=de",
      "entries": ["cn=owncloud-admindoc,cn=entry,cn=portals,cn=univention,dc=intranet,dc=wiesenthal,dc=de"],
      "name": {
        "de_DE": "Ordner 2",
        "en_US": "Ordner 2"
      }
    }
  },
  "categories": {
    "cn=domain-admin,cn=category,cn=portals,cn=univention,dc=intranet,dc=wiesenthal,dc=de": {
      "display_name": {
        "de_DE": "Verwaltung",
        "en_US": "Administration"
      },
      "dn": "cn=domain-admin,cn=category,cn=portals,cn=univention,dc=intranet,dc=wiesenthal,dc=de",
      "entries": ["cn=umc-domain,cn=entry,cn=portals,cn=univention,dc=intranet,dc=wiesenthal,dc=de", "cn=univentionblog,cn=entry,cn=portals,cn=univention,dc=intranet,dc=wiesenthal,dc=de", "cn=folder1,cn=folder,cn=portals,cn=univention,dc=intranet,dc=wiesenthal,dc=de"]
    },
    "cn=domain-service,cn=category,cn=portals,cn=univention,dc=intranet,dc=wiesenthal,dc=de": {
      "display_name": {
        "de_DE": "Applikationen",
        "en_US": "Applications"
      },
      "dn": "cn=domain-service,cn=category,cn=portals,cn=univention,dc=intranet,dc=wiesenthal,dc=de",
      "entries": ["cn=folder2,cn=folder,cn=portals,cn=univention,dc=intranet,dc=wiesenthal,dc=de", "cn=self-service,cn=entry,cn=portals,cn=univention,dc=intranet,dc=wiesenthal,dc=de", "cn=owncloud,cn=entry,cn=portals,cn=univention,dc=intranet,dc=wiesenthal,dc=de", "cn=rocketchat,cn=entry,cn=portals,cn=univention,dc=intranet,dc=wiesenthal,dc=de"]
    }
  },
  "portal": {
    "anonymousEmpty": [],
    "autoLayoutCategories": false,
    "background": null,
    "categories": ["cn=domain-service,cn=category,cn=portals,cn=univention,dc=intranet,dc=wiesenthal,dc=de", "cn=domain-admin,cn=category,cn=portals,cn=univention,dc=intranet,dc=wiesenthal,dc=de"],
    "defaultLinkTarget": "embedded",
    "dn": "cn=domain,cn=portal,cn=portals,cn=univention,dc=intranet,dc=wiesenthal,dc=de",
    "ensureLogin": false,
    "fontColor": "black",
    "logo": null,
    "name": {
      "de_DE": "Univention Portal 2",
      "en_US": "Univention Portal 2",
      "fr_FR": "Portail Univention 2"
    },
    "showApps": false,
    "content": [
      ["cn=domain-service,cn=category,cn=portals,cn=univention,dc=intranet,dc=wiesenthal,dc=de", ["cn=folder2,cn=folder,cn=portals,cn=univention,dc=intranet,dc=wiesenthal,dc=de", "cn=self-service,cn=entry,cn=portals,cn=univention,dc=intranet,dc=wiesenthal,dc=de", "cn=owncloud,cn=entry,cn=portals,cn=univention,dc=intranet,dc=wiesenthal,dc=de", "cn=rocketchat,cn=entry,cn=portals,cn=univention,dc=intranet,dc=wiesenthal,dc=de"]],
      ["cn=domain-admin,cn=category,cn=portals,cn=univention,dc=intranet,dc=wiesenthal,dc=de", ["cn=umc-domain,cn=entry,cn=portals,cn=univention,dc=intranet,dc=wiesenthal,dc=de", "cn=univentionblog,cn=entry,cn=portals,cn=univention,dc=intranet,dc=wiesenthal,dc=de", "cn=folder1,cn=folder,cn=portals,cn=univention,dc=intranet,dc=wiesenthal,dc=de"]]
    ]
  },
  "filtered": true,
  "may_edit_portal": false
}
